hydws/__init__.py
hydws/coordinates.py
hydws/client/__init__.py
hydws/client/hydws.py
hydws/parser/__init__.py
hydws/parser/parser.py
hydws/parser/rawparser.py
hydws/parser/schema.py
hydws/parser/tests/__init__.py
hydws/parser/tests/hydraulics.json
hydws/parser/tests/hydraulics.parquet
hydws/parser/tests/test_parser.py
hydws/tests/test_coordinate_transformer.py
hydws_client-1.3.1.dist-info/licenses/LICENSE
hydws_client-1.3.1.dist-info/METADATA
hydws_client-1.3.1.dist-info/WHEEL
hydws_client-1.3.1.dist-info/top_level.txt
hydws_client-1.3.1.dist-info/RECORD
