Metadata-Version: 2.4
Name: hydws-client
Version: 1.3.1
Summary: Python client library for the HYDWS web service
Author-email: Nicolas Schmid <nicolas.schmid@sed.ethz.ch>
License:                     GNU AFFERO GENERAL PUBLIC LICENSE
Project-URL: Documentation, https://github.com/swiss-seismological-service/hydws-client
Project-URL: Repository, https://github.com/swiss-seismological-service/hydws-client
Project-URL: Issues, https://github.com/swiss-seismological-service/hydws-client/issues
Classifier: Development Status :: 4 - Beta
Classifier: Environment :: Console
Classifier: Intended Audience :: Science/Research
Classifier: Intended Audience :: Education
Classifier: Operating System :: OS Independent
Classifier: License :: OSI Approved :: GNU Affero General Public License v3
Classifier: Programming Language :: Python :: 3
Classifier: Programming Language :: Python :: 3.10
Classifier: Programming Language :: Python :: 3.12
Classifier: Topic :: Scientific/Engineering
Classifier: Topic :: Scientific/Engineering :: Physics
Requires-Python: >=3.10
License-File: LICENSE
Requires-Dist: pandas
Requires-Dist: pydantic
Requires-Dist: pyproj
Requires-Dist: requests
Provides-Extra: dev
Requires-Dist: build; extra == "dev"
Requires-Dist: setuptools-scm; extra == "dev"
Requires-Dist: twine; extra == "dev"
Requires-Dist: pyarrow; extra == "dev"
Requires-Dist: pytest; extra == "dev"
Requires-Dist: isort; extra == "dev"
Requires-Dist: pytest-cov; extra == "dev"
Requires-Dist: tox; extra == "dev"
Requires-Dist: flake8; extra == "dev"
Requires-Dist: responses; extra == "dev"
Dynamic: license-file
